pdf_tools/PdfUtils.py
pdf_tools/__init__.py
pdf_tools_0311-0.1.1.dist-info/LICENSE
pdf_tools_0311-0.1.1.dist-info/METADATA
pdf_tools_0311-0.1.1.dist-info/WHEEL
pdf_tools_0311-0.1.1.dist-info/top_level.txt
pdf_tools_0311-0.1.1.dist-info/RECORD
