Metadata-Version: 2.1
Name: pdf-tools-0311
Version: 0.1.1
Summary: pdf office tool.
Home-page: https://github.com/miao111/office_master.git
Author: qr miao
Author-email: 524808594@qq.com
License: MIT
Platform: UNKNOWN
Classifier: License :: OSI Approved :: MIT License
Classifier: Programming Language :: Python
Classifier: Programming Language :: Python :: 3
Classifier: Programming Language :: Python :: 3.6
Classifier: Programming Language :: Python :: Implementation :: CPython
Classifier: Programming Language :: Python :: Implementation :: PyPy
Requires-Python: >=3.6.0
Requires-Dist: PyPDF2
Requires-Dist: PySimpleGUI
Requires-Dist: tkinter
